partialjson/__init__.py
partialjson/json_parser.py
partialjson-0.0.9.dist-info/LICENSE
partialjson-0.0.9.dist-info/METADATA
partialjson-0.0.9.dist-info/WHEEL
partialjson-0.0.9.dist-info/top_level.txt
partialjson-0.0.9.dist-info/RECORD
