Metadata-Version: 2.2
Name: partialjson
Version: 0.0.9
Summary: Parse incomplete or partial json
Home-page: https://github.com/iw4p/partialjson
Author: Nima Akbarzadeh
Author-email: iw4p@protonmail.com
License: MIT
License-File: LICENSE
Dynamic: author
Dynamic: author-email
Dynamic: description
Dynamic: description-content-type
Dynamic: home-page
Dynamic: license
Dynamic: summary
